TRH/__init__.py
TRH/main.py
TRH-2.1.dist-info/LICENSE
TRH-2.1.dist-info/METADATA
TRH-2.1.dist-info/WHEEL
TRH-2.1.dist-info/top_level.txt
TRH-2.1.dist-info/RECORD
