Metadata-Version: 2.1
Name: TRH
Version: 2.1
Summary: TypeRacer and MonkeyType Hack using Selenium Chromium Webdriver and BeatifulSoup Web Scraping.
Home-page: UNKNOWN
Author: TanmayArya1-p
Author-email: <tanmayarya2018@gmail.com>
License: UNKNOWN
Keywords: python,selenium,web-scraping
Platform: UNKNOWN
Classifier: Development Status :: 1 - Planning
Classifier: Intended Audience :: Developers
Classifier: Programming Language :: Python :: 3
Classifier: Operating System :: Unix
Classifier: Operating System :: MacOS :: MacOS X
Classifier: Operating System :: Microsoft :: Windows
Requires-Dist: selenium
Requires-Dist: beautifulsoup4
